{
    "$schema": "https://go.kicad.org/pcm/schemas/v1",
    "name": "sikit (UnsignedChad)",
    "maintainer": {
        "name": "Charles Kennedy",
        "contact": {
            "web": "https://github.com/UnsignedChad"
        }
    },
    "packages": {
        "url": "https://raw.githubusercontent.com/UnsignedChad/sikit-kicad/main/pcm/packages.json",
        "sha256": "181653940e600b4836e7031bb852cc5b86a0766095baee316f8946cf9dcb5ad6",
        "update_timestamp": 1781050821,
        "update_time_utc": "2026-06-10 00:20:21"
    }
}